tasktronaut/__init__.py
tasktronaut/backend.py
tasktronaut/builder.py
tasktronaut/context.py
tasktronaut/decorators.py
tasktronaut/errors.py
tasktronaut/process.py
tasktronaut/py.typed
tasktronaut/steps.py
tasktronaut/types.py
tasktronaut/utils.py
tasktronaut/backends/__init__.py
tasktronaut/backends/rq.py
tasktronaut-0.3.0.dist-info/licenses/LICENSE
tasktronaut-0.3.0.dist-info/METADATA
tasktronaut-0.3.0.dist-info/WHEEL
tasktronaut-0.3.0.dist-info/top_level.txt
tasktronaut-0.3.0.dist-info/RECORD
