Metadata-Version: 2.4
Name: tasktronaut
Version: 0.3.0
Summary: A simple task orchestration library for running complex processes or workflows in Python.
Author-email: Chris Stefano <virtualstaticvoid@gmail.com>
License-Expression: MIT
Project-URL: homepage, https://github.com/virtualstaticvoid/tasktronaut
Project-URL: repository, https://github.com/virtualstaticvoid/tasktronaut.git
Project-URL: changelog, https://github.com/virtualstaticvoid/tasktronaut/blob/main/CHANGELOG.md
Classifier: Development Status :: 5 - Production/Stable
Classifier: Programming Language :: Python
Classifier: Programming Language :: Python :: 3.13
Classifier: Programming Language :: Python :: 3 :: Only
Requires-Python: >=3.10
License-File: LICENSE
Requires-Dist: pydantic>=2.12.4
Dynamic: license-file
